server/__init__.py
server/config.py
server/main.py
server/api/__init__.py
server/api/exports.py
server/api/jobs.py
server/api/products.py
server/api/queries.py
server/api/router.py
server/api/scans.py
server/api/schemas.py
server/api/systems.py
server/db/__init__.py
server/db/models.py
server/db/session.py
server/storage/__init__.py
server/storage/base.py
server/storage/local.py
server/storage/s3.py
syfter/__init__.py
syfter/__main__.py
syfter/cli.py
syfter/client.py
syfter/config.py
syfter/exporter.py
syfter/manipulator.py
syfter/models.py
syfter/scanner.py
syfter/storage.py
syfter-0.9.0.1.dist-info/licenses/LICENSE.txt
syfter-0.9.0.1.dist-info/METADATA
syfter-0.9.0.1.dist-info/WHEEL
syfter-0.9.0.1.dist-info/entry_points.txt
syfter-0.9.0.1.dist-info/top_level.txt
syfter-0.9.0.1.dist-info/RECORD
