Metadata-Version: 2.4
Name: syfter
Version: 0.9.0.1
Summary: SBOM generation and management tool using Syft
Author-email: Vincent Danen <vdanen@redhat.com>
License: Apache-2.0
Project-URL: Homepage, https://github.com/vdanen/syfter
Project-URL: Repository, https://github.com/vdanen/syfter
Classifier: Development Status :: 4 - Beta
Classifier: Intended Audience :: Developers
Classifier: License :: OSI Approved :: Apache Software License
Classifier: Programming Language :: Python :: 3
Classifier: Programming Language :: Python :: 3.9
Classifier: Programming Language :: Python :: 3.10
Classifier: Programming Language :: Python :: 3.11
Classifier: Programming Language :: Python :: 3.12
Classifier: Programming Language :: Python :: 3.13
Requires-Python: >=3.9
License-File: LICENSE.txt
Requires-Dist: click>=8.0
Requires-Dist: pyyaml>=6.0
Requires-Dist: rich>=13.0
Requires-Dist: packageurl-python>=0.11
Requires-Dist: httpx>=0.25
Provides-Extra: server
Requires-Dist: fastapi>=0.109; extra == "server"
Requires-Dist: uvicorn[standard]>=0.27; extra == "server"
Requires-Dist: sqlalchemy>=2.0; extra == "server"
Requires-Dist: psycopg2-binary>=2.9; extra == "server"
Requires-Dist: boto3>=1.34; extra == "server"
Requires-Dist: python-multipart>=0.0.6; extra == "server"
Provides-Extra: dev
Requires-Dist: pytest>=7.0; extra == "dev"
Requires-Dist: pytest-cov>=4.0; extra == "dev"
Requires-Dist: black>=23.0; extra == "dev"
Requires-Dist: ruff>=0.1; extra == "dev"
Provides-Extra: all
Requires-Dist: syfter[dev,server]; extra == "all"
Dynamic: license-file
